plone.app.content-4.1.11-py3.13-nspkg.pth
plone/app/content/__init__.py
plone/app/content/catalog.py
plone/app/content/configure.zcml
plone/app/content/interfaces.py
plone/app/content/namechooser.py
plone/app/content/namechooser.txt
plone/app/content/testing.py
plone/app/content/utils.py
plone/app/content/browser/__init__.py
plone/app/content/browser/actions.py
plone/app/content/browser/adding.py
plone/app/content/browser/configure.zcml
plone/app/content/browser/constraintypes.pt
plone/app/content/browser/constraintypes.py
plone/app/content/browser/content_status_history.py
plone/app/content/browser/content_status_modify.py
plone/app/content/browser/file.py
plone/app/content/browser/folder_publish.py
plone/app/content/browser/folderfactories.pt
plone/app/content/browser/folderfactories.py
plone/app/content/browser/full_review_list.pt
plone/app/content/browser/i18n.py
plone/app/content/browser/interfaces.py
plone/app/content/browser/query.py
plone/app/content/browser/reviewlist.py
plone/app/content/browser/selection.py
plone/app/content/browser/table.pt
plone/app/content/browser/table.txt
plone/app/content/browser/tableview.py
plone/app/content/browser/vocabulary.py
plone/app/content/browser/contents/__init__.py
plone/app/content/browser/contents/configure.zcml
plone/app/content/browser/contents/copy.py
plone/app/content/browser/contents/cut.py
plone/app/content/browser/contents/defaultpage.py
plone/app/content/browser/contents/delete.py
plone/app/content/browser/contents/paste.py
plone/app/content/browser/contents/properties.py
plone/app/content/browser/contents/rearrange.py
plone/app/content/browser/contents/rename.py
plone/app/content/browser/contents/tags.py
plone/app/content/browser/contents/workflow.py
plone/app/content/browser/contents/templates/delete.pt
plone/app/content/browser/contents/templates/folder_contents.pt
plone/app/content/browser/contents/templates/properties.pt
plone/app/content/browser/contents/templates/rename.pt
plone_app_content-4.1.11.dist-info/METADATA
plone_app_content-4.1.11.dist-info/WHEEL
plone_app_content-4.1.11.dist-info/namespace_packages.txt
plone_app_content-4.1.11.dist-info/top_level.txt
plone_app_content-4.1.11.dist-info/RECORD
