Metadata-Version: 2.4
Name: plone.app.content
Version: 4.1.11
Summary: Content Views for Plone
Home-page: https://pypi.org/project/plone.app.content
Author: Plone Foundation
Author-email: plone-developers@lists.sourceforge.net
License: GPL version 2
Keywords: plone content views viewlet
Classifier: Development Status :: 5 - Production/Stable
Classifier: Environment :: Web Environment
Classifier: Framework :: Plone
Classifier: Framework :: Plone :: 6.0
Classifier: Framework :: Plone :: Core
Classifier: Framework :: Zope :: 5
Classifier: License :: OSI Approved :: GNU General Public License v2 (GPLv2)
Classifier: Operating System :: OS Independent
Classifier: Programming Language :: Python
Classifier: Programming Language :: Python :: 3.8
Classifier: Programming Language :: Python :: 3.9
Classifier: Programming Language :: Python :: 3.10
Classifier: Programming Language :: Python :: 3.11
Requires-Python: >=3.8
Requires-Dist: plone.app.dexterity
Requires-Dist: plone.app.querystring
Requires-Dist: plone.app.uuid
Requires-Dist: plone.app.vocabularies>4.1.2
Requires-Dist: plone.app.z3cform
Requires-Dist: plone.autoform
Requires-Dist: plone.base
Requires-Dist: plone.i18n
Requires-Dist: plone.folder
Requires-Dist: plone.locking
Requires-Dist: plone.memoize
Requires-Dist: plone.protect
Requires-Dist: plone.supermodel
Requires-Dist: plone.uuid
Requires-Dist: Missing
Requires-Dist: Products.MimetypesRegistry
Requires-Dist: Products.PortalTransforms
Requires-Dist: Products.statusmessages
Requires-Dist: simplejson
Requires-Dist: Zope
Requires-Dist: z3c.relationfield
Requires-Dist: z3c.form
Requires-Dist: zope.browsermenu
Provides-Extra: test
Requires-Dist: plone.app.contenttypes[test]; extra == "test"
Requires-Dist: plone.app.testing; extra == "test"
Requires-Dist: plone.dexterity; extra == "test"
Requires-Dist: plone.namedfile; extra == "test"
Requires-Dist: plone.testing; extra == "test"
Requires-Dist: zope.annotation; extra == "test"
Requires-Dist: Products.GenericSetup; extra == "test"
Dynamic: author
Dynamic: author-email
Dynamic: classifier
Dynamic: description
Dynamic: home-page
Dynamic: keywords
Dynamic: license
Dynamic: provides-extra
Dynamic: requires-dist
Dynamic: requires-python
Dynamic: summary
